<?xml version="1.0" encoding="UTF-8"?>
<!DOCTYPE suite SYSTEM "http://testng.org/testng-1.0.dtd">
<suite name="Hitachi ServiceNow Regression Suite">
	<test name="RegressionTest - English Language">
		<parameter name="browser" value="chrome"></parameter>
		<parameter name="Language" value="English"></parameter>
		<classes>
			<!-- <class name="com.servicenow.testscripts.ServiceOutageTest" /> -->
			<!-- <class name="com.servicenow.testscripts.OrderGuidesTest" /> --> 
			<!-- <class name="com.servicenow.testscripts.RegressionTest" /> -->
			<class name="com.servicenow.testscripts.FastAndFullViewTest" />
			
		</classes>
	</test>
</suite>